monitor/ms_reader.py
monitor_data/v4/br.json
monitor_data/v4/mu.json
monitor_data/v4/sg.json
rx_monitor-0.0.3.data/scripts/check_cached_ntuples
rx_monitor-0.0.3.data/scripts/check_clone
rx_monitor-0.0.3.data/scripts/check_eff_val
rx_monitor-0.0.3.data/scripts/check_isoval
rx_monitor-0.0.3.data/scripts/check_lzr_eff
rx_monitor-0.0.3.data/scripts/check_misid
rx_monitor-0.0.3.data/scripts/check_scales
rx_monitor-0.0.3.data/scripts/check_truth_eff
rx_monitor-0.0.3.data/scripts/cons_uncons_comparison
rx_monitor-0.0.3.data/scripts/plot_training_variables
rx_monitor-0.0.3.data/scripts/plot_truth_eff
rx_monitor-0.0.3.data/scripts/unconstrained_fits
rx_monitor-0.0.3.dist-info/METADATA
rx_monitor-0.0.3.dist-info/WHEEL
rx_monitor-0.0.3.dist-info/top_level.txt
rx_monitor-0.0.3.dist-info/RECORD
